LICENSE
MANIFEST.in
README.rst
setup.cfg
setup.py
jbossply/__init__.py
jbossply/jbossparser.py
jbossply/main.py
jbossply.egg-info/PKG-INFO
jbossply.egg-info/SOURCES.txt
jbossply.egg-info/dependency_links.txt
jbossply.egg-info/entry_points.txt
jbossply.egg-info/requires.txt
jbossply.egg-info/top_level.txt
jbossply/tests/__init__.py
jbossply/tests/test.py