Metadata-Version: 1.1
Name: jbossply
Version: 0.0.2
Summary: JBoss CLI output parser
Home-page: https://github.com/EnigmaBridge/jbossply
Author: Dusan Klinec (ph4r05)
Author-email: ph4r05@gmail.com
License: MIT License
